MANIFEST.in
README.md
setup.cfg
setup.py
ompp/__init__.py
ompp/omppbasicprofile.py
ompp/omppparallelloopprofile.py
ompp/omppsummarizedprofile.py
ompp.egg-info/PKG-INFO
ompp.egg-info/SOURCES.txt
ompp.egg-info/dependency_links.txt
ompp.egg-info/not-zip-safe
ompp.egg-info/top_level.txt
ompp/ompp/bin/kinst-ompp
ompp/ompp/bin/opari
ompp/ompp/bin/opari_omp.h
ompp/ompp/bin/pomp_lib.h
ompp/ompp/lib/libompp.a