Metadata-Version: 1.0
Name: ompp
Version: 1.0.1
Summary: ompp python support
Home-page: https://github.com/PasinduSenanayake/Rigel-FYP/tree/ompppackage
Author: Rigel
Author-email: pasinduath@gmail.com
License: MIT
Platform: UNKNOWN
